odoo/addons/iot_input/README.rst
odoo/addons/iot_input/__init__.py
odoo/addons/iot_input/__manifest__.py
odoo/addons/iot_input/controller/__init__.py
odoo/addons/iot_input/controller/iot_input_controller.py
odoo/addons/iot_input/examples/multi_input_values.json
odoo/addons/iot_input/i18n/iot_input.pot
odoo/addons/iot_input/models/__init__.py
odoo/addons/iot_input/models/iot_device.py
odoo/addons/iot_input/models/iot_device_input.py
odoo/addons/iot_input/models/mail_message.py
odoo/addons/iot_input/readme/CONTRIBUTORS.rst
odoo/addons/iot_input/readme/DESCRIPTION.rst
odoo/addons/iot_input/readme/USAGE.rst
odoo/addons/iot_input/security/ir.model.access.csv
odoo/addons/iot_input/static/description/icon.png
odoo/addons/iot_input/static/description/index.html
odoo/addons/iot_input/tests/__init__.py
odoo/addons/iot_input/tests/models.py
odoo/addons/iot_input/tests/test_iot_controller.py
odoo/addons/iot_input/tests/test_iot_in.py
odoo/addons/iot_input/tests/test_iot_message.py
odoo/addons/iot_input/tests/test_iot_multi_input.py
odoo/addons/iot_input/views/iot_device_input_views.xml
odoo/addons/iot_input/views/iot_device_views.xml
odoo12_addon_iot_input-12.0.1.4.2.dist-info/METADATA
odoo12_addon_iot_input-12.0.1.4.2.dist-info/WHEEL
odoo12_addon_iot_input-12.0.1.4.2.dist-info/top_level.txt
odoo12_addon_iot_input-12.0.1.4.2.dist-info/RECORD
